JSTools-1.0.dist-info/DESCRIPTION.rst
JSTools-1.0.dist-info/METADATA
JSTools-1.0.dist-info/RECORD
JSTools-1.0.dist-info/WHEEL
JSTools-1.0.dist-info/entry_points.txt
JSTools-1.0.dist-info/metadata.json
JSTools-1.0.dist-info/top_level.txt
JSTools-1.0.dist-info/zip-safe
jstools/__init__.py
jstools/bo.py
jstools/build.py
jstools/deps.py
jstools/jsmin.py
jstools/jst.py
jstools/memoize.py
jstools/merge.py
jstools/proxy.py
jstools/tsort.py
jstools/utils.py
jstools/yuicompressor.py
