Metadata-Version: 2.0
Name: JSTools
Version: 1.0
Summary: assorted python tools for building (packing, aggregating) javascript libraries
Home-page: https://github.com/camptocamp/jstools
Author: assorted
Author-email: jstools@googlegroups.com
License: various/BSDish
Keywords: javascript
Platform: UNKNOWN
Classifier: Development Status :: 3 - Alpha
Classifier: Programming Language :: JavaScript
Classifier: Topic :: Software Development :: Build Tools
Classifier: License :: OSI Approved :: BSD License
Provides-Extra: proxy
Requires-Dist: WSGIProxy; extra == 'proxy'
Provides-Extra: sphinx
Requires-Dist: Jinja2; extra == 'sphinx'
Provides-Extra: yuicompressor
Requires-Dist: Paver; extra == 'yuicompressor'
